gitlab_grabber/__init__.py
gitlab_grabber/cli/__init__.py
gitlab_grabber/cli/cli.py
gitlab_grabber/gitlab/__init__.py
gitlab_grabber/gitlab/clone_repository.py
gitlab_grabber/gitlab/project_handler.py
gitlab_grabber/http_client/__init__.py
gitlab_grabber/http_client/client.py
gitlab_grabber/logger/__init__.py
gitlab_grabber/logger/formatter.py
gitlab_grabber/logger/logger.py
gitlab_grabber/main.py
gitlab_grabber-1.0.4.dist-info/METADATA
gitlab_grabber-1.0.4.dist-info/WHEEL
gitlab_grabber-1.0.4.dist-info/entry_points.txt
gitlab_grabber-1.0.4.dist-info/RECORD
