Metadata-Version: 2.1
Name: gitlab-grabber
Version: 1.0.4
Summary: Clone all repository from gitlab
License: MIT
Author: Trusikhin Andrei
Author-email: andrei.trusikhin@gmail.com
Requires-Python: >=3.11,<4.0
Classifier: Intended Audience :: Developers
Classifier: License :: OSI Approved :: MIT License
Classifier: Operating System :: OS Independent
Classifier: Programming Language :: Python :: 3
Classifier: Programming Language :: Python :: 3.11
Classifier: Programming Language :: Python :: 3
Classifier: Programming Language :: Python :: 3.10
Classifier: Topic :: Software Development :: Libraries :: Python Modules
Requires-Dist: aiohttp (>=3.11.2,<4.0.0)
Requires-Dist: asyncio (>=3.4.3,<4.0.0)
Requires-Dist: gitpython (>=3.1.43,<4.0.0)
Project-URL: Documentation, https://github.com/Onder7994/gitlab_grabber#readme
Project-URL: Homepage, https://github.com/Onder7994/gitlab_grabber
Project-URL: Repository, https://github.com/Onder7994/gitlab_grabber
